{
  "pools": [
    {
      "rolls": 1,
      "entries": [
        {
          "type": "minecraft:item",
          "name": "minecraft:golden_sword",
          "functions": [
            {
              "function": "minecraft:set_enchantments",
              "enchantments": {
                "minecraft:fire_aspect": 10
              }
            },
            {
              "function": "minecraft:set_attributes",
              "modifiers": [
                {
                  "attribute": "minecraft:generic.attack_damage",
                  "name": "",
                  "amount": 9999999,
                  "operation": "multiply_total",
                  "id": "92fae5cf-9a4f-4ae9-8224-078252c9510e",
                  "slot": "mainhand"
                }
              ]
            },
            {
              "function": "minecraft:set_damage",
              "damage": 0
            },
            {
              "function": "minecraft:set_name",
              "name": {
                "text": "Death Blade",
                "italic": false
              }
            }
          ]
        }
      ],
      "conditions": [
        {
          "condition": "minecraft:random_chance",
          "chance": 0.12
        }
      ]
    },
    {
      "rolls": 1,
      "entries": [
        {
          "type": "minecraft:item",
          "name": "minecraft:netherite_helmet",
          "functions": [
            {
              "function": "minecraft:set_enchantments",
              "enchantments": {
                "minecraft:protection": 4
              }
            },
            {
              "function": "minecraft:set_nbt",
              "tag": "{outer.item.helmet.fire:1b,CustomModelData:8001,Unbreakable:1b}"
            },
            {
              "function": "minecraft:set_name",
              "name": {
                "text": "Fire Helmet",
                "italic": false
              }
            }
          ]
        },
        {
          "type": "minecraft:item",
          "name": "minecraft:netherite_helmet",
          "functions": [
            {
              "function": "minecraft:set_enchantments",
              "enchantments": {
                "minecraft:protection": 4
              }
            },
            {
              "function": "minecraft:set_nbt",
              "tag": "{outer.item.helmet.speed:1b,CustomModelData:8002,Unbreakable:1b}"
            },
            {
              "function": "minecraft:set_name",
              "name": {
                "text": "Speed Helmet",
                "italic": false
              }
            }
          ]
        },
        {
          "type": "minecraft:item",
          "name": "minecraft:netherite_helmet",
          "functions": [
            {
              "function": "minecraft:set_enchantments",
              "enchantments": {
                "minecraft:protection": 4
              }
            },
            {
              "function": "minecraft:set_nbt",
              "tag": "{outer.item.helmet.regen:1b,CustomModelData:8003,Unbreakable:1b}"
            },
            {
              "function": "minecraft:set_name",
              "name": {
                "text": "Regen Helmet",
                "italic": false
              }
            }
          ]
        },
        {
          "type": "minecraft:item",
          "name": "minecraft:netherite_helmet",
          "functions": [
            {
              "function": "minecraft:set_enchantments",
              "enchantments": {
                "minecraft:protection": 4
              }
            },
            {
              "function": "minecraft:set_nbt",
              "tag": "{outer.item.helmet.life:1b,CustomModelData:8004,Unbreakable:1b}"
            },
            {
              "function": "minecraft:set_name",
              "name": {
                "text": "Life Helmet",
                "italic": false
              }
            }
          ]
        },
        {
          "type": "minecraft:item",
          "name": "minecraft:netherite_helmet",
          "functions": [
            {
              "function": "minecraft:set_enchantments",
              "enchantments": {
                "minecraft:protection": 4
              }
            },
            {
              "function": "minecraft:set_nbt",
              "tag": "{outer.item.helmet.night:1b,CustomModelData:8005,Unbreakable:1b}"
            },
            {
              "function": "minecraft:set_name",
              "name": {
                "text": "Night Helmet",
                "italic": false
              }
            }
          ]
        }
      ],
      "conditions": [
        {
          "condition": "minecraft:random_chance",
          "chance": 0.15
        }
      ]
    },
    {
      "rolls": 1,
      "entries": [
        {
          "type": "minecraft:item",
          "name": "minecraft:totem_of_undying",
          "functions": [
            {
              "function": "minecraft:set_name",
              "name": {
                "text": "Fire Totem",
                "italic": false
              }
            },
            {
              "function": "minecraft:set_nbt",
              "tag": "{outer.item.totem.fire:1,CustomModelData:8001}"
            }
          ]
        },
        {
          "type": "minecraft:item",
          "name": "minecraft:totem_of_undying",
          "functions": [
            {
              "function": "minecraft:set_name",
              "name": {
                "text": "Speed Totem",
                "italic": false
              }
            },
            {
              "function": "minecraft:set_nbt",
              "tag": "{outer.item.totem.speed:1,CustomModelData:8002}"
            }
          ]
        },
        {
          "type": "minecraft:item",
          "name": "minecraft:totem_of_undying",
          "functions": [
            {
              "function": "minecraft:set_name",
              "name": {
                "text": "Regen Totem",
                "italic": false
              }
            },
            {
              "function": "minecraft:set_nbt",
              "tag": "{outer.item.totem.regen:1,CustomModelData:8003}"
            }
          ]
        },
        {
          "type": "minecraft:item",
          "name": "minecraft:totem_of_undying",
          "functions": [
            {
              "function": "minecraft:set_name",
              "name": {
                "text": "Life Totem",
                "italic": false
              }
            },
            {
              "function": "minecraft:set_nbt",
              "tag": "{outer.item.totem.life:1,CustomModelData:8004}"
            }
          ]
        },
        {
          "type": "minecraft:item",
          "name": "minecraft:totem_of_undying",
          "functions": [
            {
              "function": "minecraft:set_name",
              "name": {
                "text": "Night Totem",
                "italic": false
              }
            },
            {
              "function": "minecraft:set_nbt",
              "tag": "{outer.item.totem.night:1,CustomModelData:8005}"
            }
          ],
          "conditions": [
            {
              "condition": "minecraft:random_chance",
              "chance": 0.15
            }
          ]
        }
      ],
      "conditions": [
        {
          "condition": "minecraft:random_chance",
          "chance": 0.2
        }
      ]
    },
    {
      "rolls": 1,
      "entries": [
        {
          "type": "minecraft:item",
          "name": "minecraft:shield"
        }
      ],
      "conditions": [
        {
          "condition": "minecraft:random_chance",
          "chance": 0.3
        }
      ]
    },
    {
      "rolls": 1,
      "entries": [
        {
          "type": "minecraft:item",
          "name": "minecraft:netherite_scrap"
        }
      ],
      "functions": [
        {
          "function": "minecraft:set_name",
          "name": {
            "text": "Scrap",
            "italic": false
          }
        }
      ],
      "conditions": [
        {
          "condition": "minecraft:random_chance",
          "chance": 0.3
        }
      ]
    },
    {
      "rolls": 1,
      "entries": [
        {
          "type": "minecraft:item",
          "name": "minecraft:trident",
          "functions": [
            {
              "function": "minecraft:set_enchantments",
              "enchantments": {
                "minecraft:loyalty": 3
              }
            }
          ],
          "conditions": [
            {
              "condition": "minecraft:random_chance",
              "chance": 0.15
            }
          ]
        }
      ],
      "conditions": [
        {
          "condition": "minecraft:random_chance",
          "chance": 0.4
        }
      ]
    },
    {
      "rolls": 1,
      "entries": [
        {
          "type": "minecraft:item",
          "name": "minecraft:enchanted_golden_apple"
        }
      ],
      "conditions": [
        {
          "condition": "minecraft:random_chance",
          "chance": 0.2
        }
      ]
    },
    {
      "rolls": 1,
      "entries": [
        {
          "type": "minecraft:item",
          "name": "minecraft:nether_star",
          "functions": [
            {
              "function": "minecraft:set_name",
              "name": {
                "text": "Golden Goblet",
                "italic": false
              }
            },
            {
              "function": "minecraft:set_lore",
              "lore": [
                {
                  "text": "Legendary Artefact",
                  "color": "gold",
                  "italic": false
                },
                {
                  "text": "Collosseum Set - (1/8)",
                  "color": "gray",
                  "italic": false
                }
              ]
            },
            {
              "function": "minecraft:set_nbt",
              "tag": "{CustomModelData:8001}"
            }
          ]
        },
        {
          "type": "minecraft:item",
          "name": "minecraft:nether_star",
          "functions": [
            {
              "function": "minecraft:set_name",
              "name": {
                "text": "Lapis Manalis",
                "italic": false
              }
            },
            {
              "function": "minecraft:set_lore",
              "lore": [
                {
                  "text": "Legendary Artefact",
                  "color": "gold",
                  "italic": false
                },
                {
                  "text": "Collosseum Set - (2/8)",
                  "color": "gray",
                  "italic": false
                }
              ]
            },
            {
              "function": "minecraft:set_nbt",
              "tag": "{CustomModelData:8002}"
            }
          ]
        },
        {
          "type": "minecraft:item",
          "name": "minecraft:nether_star",
          "functions": [
            {
              "function": "minecraft:set_name",
              "name": {
                "text": "Sibylline Book",
                "italic": false
              }
            },
            {
              "function": "minecraft:set_lore",
              "lore": [
                {
                  "text": "Legendary Artefact",
                  "color": "gold",
                  "italic": false
                },
                {
                  "text": "Collosseum Set - (3/8)",
                  "color": "gray",
                  "italic": false
                }
              ]
            },
            {
              "function": "minecraft:set_nbt",
              "tag": "{CustomModelData:8003}"
            }
          ]
        },
        {
          "type": "minecraft:item",
          "name": "minecraft:nether_star",
          "functions": [
            {
              "function": "minecraft:set_name",
              "name": {
                "text": "Golden Scales",
                "italic": false
              }
            },
            {
              "function": "minecraft:set_lore",
              "lore": [
                {
                  "text": "Legendary Artefact",
                  "color": "gold",
                  "italic": false
                },
                {
                  "text": "Collosseum Set - (4/8)",
                  "color": "gray",
                  "italic": false
                }
              ]
            },
            {
              "function": "minecraft:set_nbt",
              "tag": "{CustomModelData:8004}"
            }
          ]
        },
        {
          "type": "minecraft:item",
          "name": "minecraft:nether_star",
          "functions": [
            {
              "function": "minecraft:set_name",
              "name": {
                "text": "Corona Australis",
                "italic": false
              }
            },
            {
              "function": "minecraft:set_lore",
              "lore": [
                {
                  "text": "Legendary Artefact",
                  "color": "gold",
                  "italic": false
                },
                {
                  "text": "Collosseum Set - (5/8)",
                  "color": "gray",
                  "italic": false
                }
              ]
            },
            {
              "function": "minecraft:set_nbt",
              "tag": "{CustomModelData:8005}"
            }
          ]
        }
      ],
      "conditions": [
        {
          "condition": "minecraft:random_chance",
          "chance": 0.1
        }
      ]
    }
  ]
}
